{
  "description": "Teile lustige, schräge oder verrückte Zitate mit der Welt.",
  "home": "Startseite",
  "logout": "Abmelden",
  "profile": "Profil",
  "quotly": "Quotly",
  "settings": "Einstellungen",
  "trends": "Trends",
  "feeds": {
    "suggested_profiles": "Vorgeschlagene Profile",
    "top_quotes": "Top Zitate"
  },
  "guides": {
    "cookies": "Cookies",
    "privacy_policy": "Datenschutzrichtlinien",
    "terms_of_service": "Nutzungsbedingungen"
  },
  "login": {
    "auth_info": "Indem du dich authentifizierst, stimmst du unseren <0>Nutzungsbedingungen</0> und <1>Datenschutzrichtlinien</1> sowie der <2>Nutzung der Cookies</2> zu.",
    "discord_btn": "Mit Discord autorisieren"
  },
  "markdown": {

    "table_of_contents": "Inhaltsverzeichnis"
  },
  "page_not_found": {
    "404": "404",
    "description": "Diese Seite existiert nicht. Bitte überprüfen Sie die URL oder klicken Sie auf die Schaltfläche unten, um auf die vorherige Seite zurückzukehren.",
    "return": "Zurück",
    "title": "Seite nicht gefunden"
  },
  "quote": {
    "delete": "Löschen",
    "edit": "Bearbeiten",
    "preview": "Vorschau",
    "publish": "Posten",
    "save": "Speichern",
    "share": "Teilen",
    "quote": "Quote",
    "write": "Schreiben"
  },
  "languages": {
    "de-DE": "Deutsch",
    "en-US": "English (US)"
  }
}